{
    "rules": [  
        {
            "name": "Hide show filter",
            "admin_description": "A button is created that you can show and hide filter on admin pages on",
            "pathrule": ["tidrapport","tidrapport/*"],
            "files": [
                {"name": "css/test.css","type":"css"},
                {"name": "js/test.js", "type": "js"}
             ]
        },
        {
            "name": "Test",
            "admin_description": "Test description",
            "pathrule": ["test","test/*"],
            "files": [
                 {"name": "css/test1.css", "type": "css"}

            ]
        }
     ]
}
